.gitignore
LICENSE
README.md
setup.py
qz7.term_signals.egg-info/PKG-INFO
qz7.term_signals.egg-info/SOURCES.txt
qz7.term_signals.egg-info/dependency_links.txt
qz7.term_signals.egg-info/top_level.txt
qz7/term_signals/__init__.py