Metadata-Version: 2.1
Name: qz7.term-signals
Version: 0.0.1
Summary: Functions for gracefully handling important term signals.
Home-page: http://github.com/parantapa/qz7.term_signals
Author: Parantapa Bhattacharya
Author-email: pb+pypi@parantapa.net
License: UNKNOWN
Platform: UNKNOWN
Classifier: Programming Language :: Python :: 3
Classifier: License :: OSI Approved :: MIT License
Classifier: Operating System :: OS Independent
